[
    {
      "mob": "minecraft:blaze",
      "remove": "minecraft:blaze_rod"
    },
    {
      "mob": "minecraft:blaze",
      "player": false,
      "item": "gregtech:meta_dust@103",
      "itemcount": "0-1/1-2/3-4"
    },
    {
        "mob": "minecraft:enderman",
        "remove": "minecraft:ender_pearl"
      },
      {
        "mob": "minecraft:enderman",
        "player": false,
        "item": "gregtech:meta_dust@416",
        "itemcount": "0-1/1-2/3-4"
    },
    {
        "mob": "minecraft:slime",
        "remove": "minecraft:slime_ball"
      },
      {
        "mob": "minecraft:slime",
        "player": false,
        "item": "gregtech:meta_item_1@438",
        "itemcount": "0-1/1-2/3-4"
    },
    {
        "mob": "minecraft:magma_cube",
        "remove": "minecraft:magma_cream"
      },
      {
        "mob": "minecraft:magma_cube",
        "player": false,
      "item": "gregtech:meta_dust@103",
        "itemcount": "0-1/1-2/3-4"
    }
]
